graph.py
resolver.py
sql_node.py
topological_sort.py
sql_dependency_resolver-1.1.0.dist-info/LICENSE
sql_dependency_resolver-1.1.0.dist-info/METADATA
sql_dependency_resolver-1.1.0.dist-info/WHEEL
sql_dependency_resolver-1.1.0.dist-info/top_level.txt
sql_dependency_resolver-1.1.0.dist-info/RECORD
