Metadata-Version: 2.1
Name: sql-dependency-resolver
Version: 1.1.0
Summary: A dependency resolution library that performs conflict resolution to create a topological ordering for creating and destroying SQL objects such as views, functions and indexes.
Author-email: Mustafa Mustafa <mustafaymustafa@icloud.com>
License: MIT License        
Project-URL: Homepage, https://github.com/MustafayMustafa/sql-dependency-resolution
Keywords: sql,views,topological sort
Classifier: License :: OSI Approved :: MIT License
Classifier: Programming Language :: Python
Classifier: Programming Language :: Python :: 3
License-File: LICENSE
Provides-Extra: dev
Requires-Dist: black ; extra == 'dev'
Requires-Dist: pytest ; extra == 'dev'
Requires-Dist: pytest-cov ; extra == 'dev'
